inspirare/__init__.py
inspirare/array.py
inspirare/json.py
inspirare/network.py
inspirare/pattern.py
inspirare/random.py
inspirare/system.py
inspirare/time.py
inspirare-0.1.6.dist-info/METADATA
inspirare-0.1.6.dist-info/WHEEL
inspirare-0.1.6.dist-info/licenses/LICENSE
inspirare-0.1.6.dist-info/RECORD
